DiscordBotIHK/__init__.py
DiscordBotIHK/Bot/Bot.py
DiscordBotIHK/Bot/Calculator.py
DiscordBotIHK/Bot/DatabaseConnector.py
DiscordBotIHK/Bot/DocumentSender.py
DiscordBotIHK/Bot/Meme.py
DiscordBotIHK/Bot/SendImage.py
DiscordBotIHK/Bot/__init__.py
Discord_Bot_IHK-1.1.9.4.dist-info/METADATA
Discord_Bot_IHK-1.1.9.4.dist-info/WHEEL
Discord_Bot_IHK-1.1.9.4.dist-info/top_level.txt
Discord_Bot_IHK-1.1.9.4.dist-info/RECORD
